football_manager_scouting/__init__.py
football_manager_scouting/index.py
football_manager_scouting/insert_data.py
football_manager_scouting/spider.py
football_manager_scouting/backend/__init__.py
football_manager_scouting/backend/errors.py
football_manager_scouting/backend/player.py
football_manager_scouting/backend/preprocess_data.py
football_manager_scouting/backend/request_data.py
football_manager_scouting/backend/score.py
football_manager_scouting/backend/server.py
football_manager_scouting/backend/tables.py
football_manager_scouting/category_mappings/__init__.py
football_manager_scouting/category_mappings/categories.py
football_manager_scouting/category_mappings/category_map.py
football_manager_scouting-0.1.17.dist-info/LICENSE
football_manager_scouting-0.1.17.dist-info/METADATA
football_manager_scouting-0.1.17.dist-info/WHEEL
football_manager_scouting-0.1.17.dist-info/top_level.txt
football_manager_scouting-0.1.17.dist-info/RECORD
