Metadata-Version: 2.1
Name: football_manager_scouting
Version: 0.1.17
Summary: A Football Manager data-based scouting tool.
Author-email: Hannes Lindbäck <hanneskarllindback@gmail.com>
Maintainer-email: Hannes Lindbäck <hanneskarllindback@gmail.com>
License: 
Project-URL: Homepage, https://github.com/HannesLindback/Football-Manager-scouting
Project-URL: Documentation, https://github.com/HannesLindback/Football-Manager-scouting
Project-URL: Repository, https://github.com/HannesLindback/Football-Manager-scouting
Keywords: Football Manager,FM
Classifier: Programming Language :: Python
Requires-Python: >=3.8
License-File: LICENSE
